lmsquery/__init__.py
lmsquery/const.py
lmsquery/lmsquery.py
LMSQuery_fork-0.5.25.dist-info/LICENSE
LMSQuery_fork-0.5.25.dist-info/METADATA
LMSQuery_fork-0.5.25.dist-info/WHEEL
LMSQuery_fork-0.5.25.dist-info/top_level.txt
LMSQuery_fork-0.5.25.dist-info/RECORD
