Metadata-Version: 2.1
Name: LMSQuery-fork
Version: 0.5.25
Summary: Query library for Logitech Media Server
Home-page: https://github.com/txoof/lmsquery
Author: Robert Einhausi, Aaron Ciuffo
Author-email: aaron.ciuffo@gmail.com
License: MIT
Keywords: logitech media server lms
Platform: UNKNOWN
Classifier: Development Status :: 5 - Production/Stable
Classifier: Environment :: Console
Classifier: Intended Audience :: Developers
Classifier: License :: OSI Approved :: MIT License
Classifier: Operating System :: OS Independent
Classifier: Programming Language :: Python
Classifier: Topic :: Software Development
Classifier: Topic :: Software Development :: Libraries
Classifier: Topic :: Software Development :: Libraries :: Python Modules
Requires-Dist: requests
